MANIFEST.in
README.rst
setup.py
madame/__init__.py
madame/app.py
madame/default_settings.py
madame/utils.py
madame/validator.py
madame.egg-info/PKG-INFO
madame.egg-info/SOURCES.txt
madame.egg-info/dependency_links.txt
madame.egg-info/requires.txt
madame.egg-info/top_level.txt