Metadata-Version: 1.1
Name: madame
Version: 0.1
Summary: RESTful API for MongoDB built on Flask
Home-page: http://github.com/asdine/madame
Author: Asdine El Hrychy
Author-email: asdine.elhrychy@gmail.com
License: UNKNOWN
Platform: UNKNOWN
Classifier: Programming Language :: Python
Classifier: Development Status :: 3 - Alpha
Classifier: License :: OSI Approved :: MIT License
Classifier: Natural Language :: English
Classifier: Operating System :: OS Independent
Classifier: Programming Language :: Python :: 2.7
Classifier: Topic :: Internet :: WWW/HTTP :: Dynamic Content
Classifier: Intended Audience :: Developers
Classifier: Environment :: Web Environment
